ha_remote_tts/__init__.py
ha_remote_tts/exception.py
ha_remote_tts/lib.py
ha_remote_tts-0.1.4.dist-info/LICENSE
ha_remote_tts-0.1.4.dist-info/METADATA
ha_remote_tts-0.1.4.dist-info/WHEEL
ha_remote_tts-0.1.4.dist-info/RECORD
